dsf_enginexai_sdk/__init__.py
dsf_enginexai_sdk/client.py
dsf_enginexai_sdk/exceptions.py
dsf_enginexai_sdk-1.0.2.dist-info/licenses/LICENSE
dsf_enginexai_sdk-1.0.2.dist-info/METADATA
dsf_enginexai_sdk-1.0.2.dist-info/WHEEL
dsf_enginexai_sdk-1.0.2.dist-info/top_level.txt
dsf_enginexai_sdk-1.0.2.dist-info/RECORD
