Metadata-Version: 2.4
Name: dsf-enginexai-sdk
Version: 1.0.2
Summary: Explainable AI Scoring SDK with LLM Integration for Transparent Risk Assessment
Home-page: https://github.com/jaimeajl/dsf-enginexai-sdk
Author: Jaime Alexander Jimenez
Author-email: Jaime Alexander Jimenez Lozano <contacto@dsfuptech.cloud>
License: Proprietary
Project-URL: Homepage, https://github.com/jaimeajl/dsf-enginexai-sdk
Project-URL: Documentation, https://dsfuptech.cloud/docs
Project-URL: Bug Tracker, https://github.com/jaimeajl/dsf-enginexai-sdk/issues
Project-URL: Source, https://github.com/jaimeajl/dsf-enginexai-sdk
Project-URL: API Endpoint, https://dsf-scoring-h7y7tiqp6-api-dsfuptech.vercel.app/
Keywords: explainable-ai,xai,llm-integration,credit-scoring,risk-assessment,adaptive-learning,transparency,compliance,fintech
Classifier: Development Status :: 5 - Production/Stable
Classifier: Intended Audience :: Developers
Classifier: Intended Audience :: Financial and Insurance Industry
Classifier: Programming Language :: Python :: 3
Classifier: Programming Language :: Python :: 3.8
Classifier: Programming Language :: Python :: 3.9
Classifier: Programming Language :: Python :: 3.10
Classifier: Programming Language :: Python :: 3.11
Classifier: Programming Language :: Python :: 3.12
Classifier: License :: Other/Proprietary License
Classifier: Operating System :: OS Independent
Classifier: Topic :: Software Development :: Libraries :: Python Modules
Classifier: Topic :: Scientific/Engineering :: Artificial Intelligence
Classifier: Topic :: Office/Business :: Financial
Requires-Python: >=3.8
License-File: LICENSE
Requires-Dist: requests>=2.25.0
Dynamic: author
Dynamic: home-page
Dynamic: license-file
Dynamic: requires-python
